{
  "projectFileManifest": {
    "projectName": "Lifeflow",
    "version": "1.0.0",
    "createdDate": "2025-03-04",
    "description": "Complete file manifest for all Lifeflow project assets created during development",
    "totalFiles": 13,
    "lastUpdated": "2025-03-04"
  },
  "files": {
    "documentation": [
      {
        "filename": "REQUIREMENTS.md",
        "format": "Markdown",
        "type": "Functional & Non-Functional Requirements",
        "size": "~3KB",
        "description": "Complete requirements specification including functional requirements, non-functional requirements, and user stories",
        "contents": {
          "sections": [
            "Functional Requirements (6 items)",
            "Non-Functional Requirements (5 items)",
            "User Stories (5 stories)"
          ]
        },
        "fileType": "Text Documentation",
        "downloadable": true,
        "jsonVersion": "lifeflow-requirements.json"
      },
      {
        "filename": "README.md",
        "format": "Markdown",
        "type": "Project Overview & Getting Started",
        "size": "~2KB",
        "description": "Project overview, vision, features, tech stack, and installation instructions",
        "contents": {
          "sections": [
            "Project Overview",
            "Vision",
            "Features",
            "Tech Stack",
            "Getting Started",
            "Prerequisites",
            "Installation"
          ]
        },
        "fileType": "Text Documentation",
        "downloadable": true
      },
      {
        "filename": "PROJECT_PLAN.md",
        "format": "Markdown",
        "type": "Project Plan & Roadmap",
        "size": "~2.5KB",
        "description": "Detailed project plan with scope, MVP features, architecture, and development roadmap",
        "contents": {
          "sections": [
            "Project Scope",
            "MVP Features (6 features)",
            "Architecture Overview",
            "Technical Requirements",
            "Development Roadmap (5 phases)"
          ]
        },
        "fileType": "Text Documentation",
        "downloadable": true
      },
      {
        "filename": "DESIGN.md",
        "format": "Markdown",
        "type": "Design System & UI/UX",
        "size": "~2KB",
        "description": "Design system documentation including colors, typography, components, and wireframes",
        "contents": {
          "sections": [
            "Design System",
            "Colors",
            "Typography",
            "Components (Buttons, Forms)",
            "Wireframes"
          ]
        },
        "fileType": "Text Documentation",
        "downloadable": true,
        "jsonVersion": "lifeflow-design-system.json"
      }
    ],
    "configuration": [
      {
        "filename": "package.json",
        "format": "JSON",
        "type": "Frontend Configuration",
        "size": "~1KB",
        "description": "React frontend dependencies and build scripts",
        "contents": {
          "dependencies": [
            "react@^17.0.2",
            "react-dom@^17.0.2",
            "typescript@^4.4.4"
          ],
          "devDependencies": [
            "@testing-library/react",
            "@testing-library/jest-dom",
            "autoprefixer",
            "tailwindcss"
          ],
          "scripts": [
            "start",
            "build",
            "test",
            "eject"
          ]
        },
        "fileType": "Configuration",
        "downloadable": true
      },
      {
        "filename": "package__1_.json",
        "format": "JSON",
        "type": "Backend Configuration",
        "size": "~0.5KB",
        "description": "Node.js/Express backend dependencies",
        "contents": {
          "dependencies": [
            "express@^4.17.1",
            "mongoose@^5.11.15",
            "jsonwebtoken@^8.5.1",
            "bcryptjs@^2.4.3"
          ],
          "scripts": [
            "start"
          ]
        },
        "fileType": "Configuration",
        "downloadable": true
      },
      {
        "filename": "gitignore.txt",
        "format": "Text",
        "type": "Git Configuration",
        "size": "~0.3KB",
        "description": "Git ignore patterns for the project",
        "contents": {
          "ignoredPatterns": [
            "node_modules/",
            "dist/",
            ".next/",
            ".env"
          ]
        },
        "fileType": "Configuration",
        "downloadable": true
      }
    ],
    "components": [
      {
        "filename": "Lifeflow-MVP.jsx",
        "format": "JSX/React",
        "type": "Main Application Component",
        "size": "~25KB",
        "description": "Complete React MVP component with all features including authentication, task management, goal tracking, dashboard, and settings",
        "contents": {
          "features": [
            "User Authentication (Login/Signup)",
            "Task Management (CRUD)",
            "Goal Tracking with Progress",
            "Dashboard with Statistics",
            "Calendar View",
            "Settings Page",
            "Responsive Design"
          ],
          "pages": [
            "Login Page",
            "Dashboard",
            "Tasks",
            "Goals",
            "Calendar",
            "Settings"
          ],
          "dependencies": [
            "React",
            "Lucide React Icons",
            "Tailwind CSS"
          ]
        },
        "fileType": "React Component",
        "downloadable": true,
        "status": "Active & Tested",
        "componentCount": 1,
        "linesOfCode": "~650"
      }
    ],
    "jsonAssets": [
      {
        "filename": "lifeflow-project-manifest.json",
        "format": "JSON",
        "type": "Project Manifest",
        "size": "~8KB",
        "description": "Comprehensive project manifest with all metadata, features, roadmap, design system, and configuration",
        "contents": {
          "sections": [
            "Project Metadata",
            "Tech Stack",
            "Features",
            "MVP Requirements",
            "User Stories",
            "Development Roadmap",
            "Design System",
            "Deployment Info",
            "Files Index",
            "Git Configuration",
            "Success Metrics",
            "Next Steps"
          ]
        },
        "fileType": "JSON Asset",
        "downloadable": true,
        "createdFrom": "All documentation and project files"
      },
      {
        "filename": "lifeflow-requirements.json",
        "format": "JSON",
        "type": "Requirements Specification",
        "size": "~5KB",
        "description": "JSON version of requirements with functional, non-functional requirements, and user stories",
        "contents": {
          "sections": [
            "Functional Requirements (6 items)",
            "Non-Functional Requirements (5 items)",
            "User Stories (5 stories)",
            "Constraints",
            "Out of Scope"
          ]
        },
        "fileType": "JSON Asset",
        "downloadable": true,
        "basedOn": "REQUIREMENTS.md"
      },
      {
        "filename": "lifeflow-design-system.json",
        "format": "JSON",
        "type": "Design System",
        "size": "~12KB",
        "description": "Complete design system with colors, typography, components, layouts, and accessibility guidelines",
        "contents": {
          "sections": [
            "Colors",
            "Typography",
            "Spacing",
            "Border Radius",
            "Shadows",
            "Components (Buttons, Forms, Cards, Progress)",
            "Layouts",
            "Responsive Breakpoints",
            "Accessibility (WCAG 2.1 AA)",
            "Animations & Transitions"
          ]
        },
        "fileType": "JSON Asset",
        "downloadable": true,
        "basedOn": "DESIGN.md"
      },
      {
        "filename": "lifeflow-components.json",
        "format": "JSON",
        "type": "Components Documentation",
        "size": "~10KB",
        "description": "Detailed documentation of all React components, data models, and API endpoints",
        "contents": {
          "sections": [
            "Component Documentation (LifeflowMVP)",
            "Data Models (User, Task, Goal, Notification)",
            "API Endpoints (Auth, Tasks, Goals)",
            "UI Components (Login, Header, Cards, Forms)"
          ]
        },
        "fileType": "JSON Asset",
        "downloadable": true,
        "basedOn": "Lifeflow-MVP.jsx"
      },
      {
        "filename": "lifeflow-config.json",
        "format": "JSON",
        "type": "Project Configuration",
        "size": "~18KB",
        "description": "Complete project configuration including frontend, backend, database, deployment, security, testing, and monitoring",
        "contents": {
          "sections": [
            "Frontend Configuration",
            "Backend Configuration",
            "Database Configuration",
            "Environment Variables",
            "Deployment Configuration",
            "Git Configuration",
            "Security Configuration",
            "Testing Configuration",
            "CI/CD Configuration",
            "Performance Configuration",
            "Scalability Configuration",
            "Monitoring"
          ]
        },
        "fileType": "JSON Asset",
        "downloadable": true
      },
      {
        "filename": "lifeflow-project-manifest.json (this file)",
        "format": "JSON",
        "type": "File Manifest & Index",
        "size": "~15KB",
        "description": "Complete index and manifest of all project files with descriptions and organization",
        "contents": {
          "sections": [
            "Documentation Files",
            "Configuration Files",
            "Component Files",
            "JSON Assets",
            "File Statistics"
          ]
        },
        "fileType": "JSON Asset",
        "downloadable": true
      }
    ]
  },
  "fileStatistics": {
    "totalFiles": 13,
    "byType": {
      "documentation": 4,
      "configuration": 3,
      "components": 1,
      "jsonAssets": 6
    },
    "byFormat": {
      "markdown": 4,
      "json": 6,
      "jsx": 1,
      "text": 1,
      "javascript": 1
    },
    "estimatedTotalSize": "~115 KB",
    "downloadsAvailable": 13
  },
  "organizationStructure": {
    "documentation": {
      "purpose": "Project specifications and planning",
      "files": [
        "REQUIREMENTS.md",
        "README.md",
        "PROJECT_PLAN.md",
        "DESIGN.md"
      ]
    },
    "configuration": {
      "purpose": "Setup and deployment configuration",
      "files": [
        "package.json",
        "package__1_.json",
        "gitignore.txt"
      ]
    },
    "source": {
      "purpose": "Application code",
      "files": [
        "Lifeflow-MVP.jsx"
      ]
    },
    "jsonAssets": {
      "purpose": "Structured data and specifications",
      "files": [
        "lifeflow-project-manifest.json",
        "lifeflow-requirements.json",
        "lifeflow-design-system.json",
        "lifeflow-components.json",
        "lifeflow-config.json",
        "lifeflow-project-manifest.json"
      ]
    }
  },
  "quickLinks": {
    "getStarted": "See README.md for installation instructions",
    "requirements": "See REQUIREMENTS.md and lifeflow-requirements.json",
    "design": "See DESIGN.md and lifeflow-design-system.json",
    "components": "See Lifeflow-MVP.jsx and lifeflow-components.json",
    "configuration": "See lifeflow-config.json for complete configuration",
    "projectPlan": "See PROJECT_PLAN.md for roadmap and phases"
  },
  "usageGuide": {
    "allInOne": "Start with lifeflow-project-manifest.json for complete project overview",
    "development": "Use package.json and Lifeflow-MVP.jsx to start development",
    "deployment": "Reference lifeflow-config.json for deployment and environment setup",
    "design": "Follow lifeflow-design-system.json for UI/UX consistency",
    "api": "See lifeflow-components.json for API endpoint specifications"
  },
  "nextSteps": [
    {
      "step": 1,
      "title": "Review Project Specifications",
      "files": ["REQUIREMENTS.md", "PROJECT_PLAN.md", "lifeflow-project-manifest.json"]
    },
    {
      "step": 2,
      "title": "Set Up Development Environment",
      "files": ["package.json", "package__1_.json", "lifeflow-config.json"],
      "commands": [
        "npm install (frontend)",
        "npm install (backend)",
        "Set up MongoDB"
      ]
    },
    {
      "step": 3,
      "title": "Review Design System",
      "files": ["DESIGN.md", "lifeflow-design-system.json"]
    },
    {
      "step": 4,
      "title": "Start Development",
      "files": ["Lifeflow-MVP.jsx", "lifeflow-components.json"],
      "tasks": [
        "Connect frontend to backend API",
        "Implement authentication endpoints",
        "Create database models"
      ]
    },
    {
      "step": 5,
      "title": "Testing & Deployment",
      "files": ["lifeflow-config.json"],
      "phases": ["Unit Testing", "Integration Testing", "Staging Deployment", "Production Deployment"]
    }
  ],
  "downloadInstructions": {
    "note": "All files are available for download from the outputs folder",
    "formats": [
      "Individual files can be downloaded separately",
      "All JSON files are properly formatted and validated",
      "All markdown files are ready to use"
    ],
    "recommendations": [
      "Start with lifeflow-project-manifest.json for overview",
      "Keep lifeflow-config.json for environment setup",
      "Use lifeflow-components.json as development reference",
      "Follow REQUIREMENTS.md during development",
      "Reference DESIGN.md for UI consistency"
    ]
  },
  "metadata": {
    "projectVersion": "1.0.0",
    "mspVersion": "MVP Phase",
    "createdDate": "2025-03-04",
    "lastUpdated": "2025-03-04",
    "totalLines": "~750 lines of code + ~5000 lines of documentation",
    "status": "Ready for Development",
    "compatibility": "React 17+, Node 14+, MongoDB 4.0+"
  }
}
